meeshkan/__init__.py
meeshkan/__main__.py
meeshkan/config.py
meeshkan/logger.py
meeshkan/logging.yaml
meeshkan/meeshkan_types.py
meeshkan/prepare.py
meeshkan/build/__init__.py
meeshkan/build/builder.py
meeshkan/build/json_schema.py
meeshkan/build/media_types.py
meeshkan/build/operation.py
meeshkan/build/param.py
meeshkan/build/paths.py
meeshkan/build/result.py
meeshkan/build/schemadiff.py
meeshkan/build/servers.py
meeshkan/build/update_mode.py
meeshkan/build/writer.py
meeshkan/serve/__init__.py
meeshkan/serve/commands.py
meeshkan/serve/admin/__init__.py
meeshkan/serve/admin/runner.py
meeshkan/serve/admin/views.py
meeshkan/serve/mock/__init__.py
meeshkan/serve/mock/callbacks.py
meeshkan/serve/mock/faker.py
meeshkan/serve/mock/log.py
meeshkan/serve/mock/matcher.py
meeshkan/serve/mock/response_matcher.py
meeshkan/serve/mock/rest.py
meeshkan/serve/mock/scope.py
meeshkan/serve/mock/security.py
meeshkan/serve/mock/server.py
meeshkan/serve/mock/specs.py
meeshkan/serve/mock/storage.py
meeshkan/serve/mock/views.py
meeshkan/serve/record/__init__.py
meeshkan/serve/record/channel.py
meeshkan/serve/record/proxy.py
meeshkan/serve/record/proxy_callback.py
meeshkan/serve/utils/__init__.py
meeshkan/serve/utils/data_callback.py
meeshkan/serve/utils/http_utils.py
meeshkan/serve/utils/routing.py
meeshkan/sinks/__init__.py
meeshkan/sinks/abstract.py
meeshkan/sinks/file.py
meeshkan/sources/__init__.py
meeshkan/sources/abstract.py
meeshkan/sources/file.py
meeshkan/sources/kafka.py
meeshkan/tutorial/__init__.py
tests/build/__init__.py
tests/build/test_builder.py
tests/build/test_json_schema.py
tests/build/test_paths.py
tests/build/test_query.py
tests/build/test_servers.py
tests/serve/__init__.py
tests/serve/mock/__init__.py
tests/serve/mock/test_callbacks.py
tests/serve/mock/test_control_via_rest.py
tests/serve/mock/test_faker.py
tests/serve/mock/test_matcher.py
tests/serve/mock/test_matcher_helper_functions.py
tests/serve/mock/test_mocking_server_gen_fails.py
meeshkan-0.2.25.dist-info/LICENSE
meeshkan-0.2.25.dist-info/METADATA
meeshkan-0.2.25.dist-info/WHEEL
meeshkan-0.2.25.dist-info/entry_points.txt
meeshkan-0.2.25.dist-info/top_level.txt
meeshkan-0.2.25.dist-info/RECORD
