Metadata-Version: 2.1
Name: meeshkan
Version: 0.2.25
Summary: Reverse engineer services with style
Home-page: http://github.com/meeshkan/meeshkan
Author: Meeshkan Dev Team
Author-email: dev@meeshkan.com
License: MIT
Platform: UNKNOWN
Classifier: Programming Language :: Python :: 3
Classifier: License :: OSI Approved :: MIT License
Classifier: Operating System :: OS Independent
Requires-Python: >=3.6.0
Requires-Dist: click (==7.0)
Requires-Dist: lenses
Requires-Dist: pyyaml
Requires-Dist: jsonschema
Requires-Dist: faker
Requires-Dist: requests
Requires-Dist: typing-extensions
Requires-Dist: openapi-typed-2 (>=0.0.4)
Requires-Dist: typeguard (>=2.7.0)
Requires-Dist: genson
Requires-Dist: http-types (<0.1.0,>=0.0.15)
Requires-Dist: faust
Requires-Dist: tornado (==5.1.1)
Requires-Dist: urllib3 (==1.25.6)
Requires-Dist: meeshkan-daemonocle
Requires-Dist: clint
Requires-Dist: pyfiglet
Requires-Dist: progress
Requires-Dist: psutil (>=5.6.3)
Requires-Dist: dataclasses ; python_version < "3.7"
Provides-Extra: dev
Requires-Dist: black (==19.10b0) ; extra == 'dev'
Requires-Dist: flake8 ; extra == 'dev'
Requires-Dist: isort ; extra == 'dev'
Requires-Dist: mypy ; extra == 'dev'
Requires-Dist: pyhamcrest ; extra == 'dev'
Requires-Dist: pylint ; extra == 'dev'
Requires-Dist: pytest ; extra == 'dev'
Requires-Dist: pytest-asyncio ; extra == 'dev'
Requires-Dist: pytest-testmon ; extra == 'dev'
Requires-Dist: pytest-tornado ; extra == 'dev'
Requires-Dist: pytest-watch ; extra == 'dev'
Requires-Dist: requests-mock ; extra == 'dev'
Requires-Dist: setuptools ; extra == 'dev'
Requires-Dist: twine ; extra == 'dev'
Requires-Dist: wheel ; extra == 'dev'
